[{"type":"node","id":"2","labels":["CLASS"],"properties":{"name":"User","strict":true,"uri":"schema-1"}},
 {"type":"node","id":"3","labels":["PROPERTY"],"properties":{"name":"user_id","dtype":"int","uri":"schema-2","required":true}},
 {"type":"node","id":"4","labels":["PROPERTY"],"properties":{"name":"username","uri":"schema-3","required":true}},
 {"type":"node","id":"5","labels":["PROPERTY"],"properties":{"name":"password","uri":"schema-4","required":true}},
 {"type":"node","id":"6","labels":["PROPERTY"],"properties":{"name":"email","uri":"schema-5"}},
 {"type":"node","id":"7","labels":["PROPERTY"],"properties":{"name":"admin","dtype":"bool","uri":"schema-6"}},
 {"type":"node","id":"22","labels":["PROPERTY"],"properties":{"name":"url","uri":"schema-64"}},
 {"type":"node","id":"25","labels":["CLASS"],"properties":{"name":"Content Item","strict":false,"uri":"schema-15","no_datanodes":true}},
 {"type":"node","id":"26","labels":["CLASS"],"properties":{"code":"cat","name":"Categories","strict":false,"uri":"schema-16"}},
 {"type":"node","id":"27","labels":["PROPERTY"],"properties":{"name":"name","uri":"schema-17"}},
 {"type":"node","id":"28","labels":["PROPERTY"],"properties":{"name":"remarks","uri":"schema-18"}},
 {"type":"node","id":"32","labels":["CLASS"],"properties":{"code":"r","name":"Records","strict":false,"uri":"schema-22","no_datanodes":true}},
 {"type":"node","id":"33","labels":["CLASS"],"properties":{"code":"n","name":"Notes","strict":false,"uri":"schema-23"}},
 {"type":"node","id":"34","labels":["CLASS"],"properties":{"code":"i","name":"Images","strict":false,"uri":"schema-77"}},
 {"type":"node","id":"35","labels":["PROPERTY"],"properties":{"name":"width","uri":"schema-78"}},
 {"type":"node","id":"36","labels":["PROPERTY"],"properties":{"name":"caption","uri":"schema-79"}},
 {"type":"node","id":"37","labels":["CLASS"],"properties":{"code":"h","name":"Headers","strict":false,"uri":"schema-31"}},
 {"type":"node","id":"38","labels":["PROPERTY"],"properties":{"name":"text","uri":"schema-32"}},
 {"type":"node","id":"66","labels":["CLASS"],"properties":{"name":"Media","strict":false,"uri":"schema-60","no_datanodes":true}},
 {"type":"node","id":"67","labels":["PROPERTY"],"properties":{"name":"basename","uri":"schema-61"}},
 {"type":"node","id":"68","labels":["PROPERTY"],"properties":{"name":"suffix","uri":"schema-62"}},
 {"type":"node","id":"69","labels":["CLASS"],"properties":{"code":"sl","name":"Site Link","strict":false,"uri":"schema-63"}},
 {"type":"node","id":"70","labels":["PROPERTY"],"properties":{"name":"name","uri":"schema-65"}},
 {"type":"node","id":"71","labels":["PROPERTY"],"properties":{"name":"date","uri":"schema-66"}},
 {"type":"node","id":"72","labels":["PROPERTY"],"properties":{"name":"comments","uri":"schema-67"}},
 {"type":"node","id":"73","labels":["PROPERTY"],"properties":{"name":"rating","uri":"schema-68"}},
 {"type":"node","id":"74","labels":["PROPERTY"],"properties":{"name":"read","uri":"schema-69"}},
 {"type":"node","id":"77","labels":["CLASS"],"properties":{"name":"Collections","strict":false,"uri":"schema-72","no_datanodes":true}},
 {"type":"node","id":"82","labels":["CLASS"],"properties":{"code":"d","name":"Document","strict":false,"uri":"schema-80"}},
 {"type":"node","id":"83","labels":["PROPERTY"],"properties":{"name":"caption","uri":"schema-81"}},
 {"type":"node","id":"84","labels":["PROPERTY"],"properties":{"name":"title","uri":"schema-82"}},
 {"type":"node","id":"103","labels":["CLASS"],"properties":{"name":"Import Data","strict":false,"uri":"schema-101"}},
 {"type":"node","id":"104","labels":["PROPERTY"],"properties":{"name":"date","uri":"schema-102"}},
 {"type":"node","id":"105","labels":["PROPERTY"],"properties":{"name":"source","uri":"schema-103"}},
 {"type":"node","id":"113","labels":["CLASS"],"properties":{"name":"Indexer","strict":false,"uri":"schema-111"}},
 {"type":"node","id":"114","labels":["CLASS"],"properties":{"name":"Word","strict":false,"uri":"schema-112"}},
 {"type":"node","id":"115","labels":["PROPERTY"],"properties":{"name":"name","uri":"schema-113"}},
 {"type":"node","id":"130","labels":["PROPERTY"],"properties":{"name":"height","uri":"schema-129"}},
 {"type":"node","id":"131","labels":["PROPERTY"],"properties":{"name":"description","uri":"schema-133"}},
 {"type":"node","id":"132","labels":["CLASS"],"properties":{"name":"Plugin","strict":false,"uri":"schema-130"}},
 {"type":"node","id":"133","labels":["PROPERTY"],"properties":{"name":"code","uri":"schema-131"}},
 {"type":"node","id":"134","labels":["PROPERTY"],"properties":{"name":"location","uri":"schema-132"}},
 {"type":"relationship","id":"0","label":"HAS_PROPERTY","properties":{"index":1},"start":{"id":"2","labels":["CLASS"],"properties":{"name":"User","strict":true,"uri":"schema-1"}},"end":{"id":"3","labels":["PROPERTY"],"properties":{"name":"user_id","dtype":"int","uri":"schema-2","required":true}}},
 {"type":"relationship","id":"1","label":"HAS_PROPERTY","properties":{"index":2},"start":{"id":"2","labels":["CLASS"],"properties":{"name":"User","strict":true,"uri":"schema-1"}},"end":{"id":"4","labels":["PROPERTY"],"properties":{"name":"username","uri":"schema-3","required":true}}},
 {"type":"relationship","id":"2","label":"HAS_PROPERTY","properties":{"index":3},"start":{"id":"2","labels":["CLASS"],"properties":{"name":"User","strict":true,"uri":"schema-1"}},"end":{"id":"5","labels":["PROPERTY"],"properties":{"name":"password","uri":"schema-4","required":true}}},
 {"type":"relationship","id":"3","label":"HAS_PROPERTY","properties":{"index":4},"start":{"id":"2","labels":["CLASS"],"properties":{"name":"User","strict":true,"uri":"schema-1"}},"end":{"id":"6","labels":["PROPERTY"],"properties":{"name":"email","uri":"schema-5"}}},
 {"type":"relationship","id":"4","label":"HAS_PROPERTY","properties":{"index":5},"start":{"id":"2","labels":["CLASS"],"properties":{"name":"User","strict":true,"uri":"schema-1"}},"end":{"id":"7","labels":["PROPERTY"],"properties":{"name":"admin","dtype":"bool","uri":"schema-6"}}},
 {"type":"relationship","id":"68","label":"HAS_PROPERTY","properties":{"index":1},"start":{"id":"34","labels":["CLASS"],"properties":{"code":"i","name":"Images","strict":false,"uri":"schema-77"}},"end":{"id":"35","labels":["PROPERTY"],"properties":{"name":"width","uri":"schema-78"}}},
 {"type":"relationship","id":"69","label":"HAS_PROPERTY","properties":{"index":2},"start":{"id":"34","labels":["CLASS"],"properties":{"code":"i","name":"Images","strict":false,"uri":"schema-77"}},"end":{"id":"36","labels":["PROPERTY"],"properties":{"name":"caption","uri":"schema-79"}}},
 {"type":"relationship","id":"70","label":"INSTANCE_OF","start":{"id":"34","labels":["CLASS"],"properties":{"code":"i","name":"Images","strict":false,"uri":"schema-77"}},"end":{"id":"66","labels":["CLASS"],"properties":{"name":"Media","strict":false,"uri":"schema-60","no_datanodes":true}}},
 {"type":"relationship","id":"134","label":"HAS_PROPERTY","properties":{"index":1},"start":{"id":"103","labels":["CLASS"],"properties":{"name":"Import Data","strict":false,"uri":"schema-101"}},"end":{"id":"104","labels":["PROPERTY"],"properties":{"name":"date","uri":"schema-102"}}},
 {"type":"relationship","id":"136","label":"HAS_PROPERTY","properties":{"index":2},"start":{"id":"103","labels":["CLASS"],"properties":{"name":"Import Data","strict":false,"uri":"schema-101"}},"end":{"id":"105","labels":["PROPERTY"],"properties":{"name":"source","uri":"schema-103"}}},
 {"type":"relationship","id":"73","label":"HAS_PROPERTY","properties":{"index":1},"start":{"id":"69","labels":["CLASS"],"properties":{"code":"sl","name":"Site Link","strict":false,"uri":"schema-63"}},"end":{"id":"22","labels":["PROPERTY"],"properties":{"name":"url","uri":"schema-64"}}},
 {"type":"relationship","id":"74","label":"HAS_PROPERTY","properties":{"index":2},"start":{"id":"69","labels":["CLASS"],"properties":{"code":"sl","name":"Site Link","strict":false,"uri":"schema-63"}},"end":{"id":"70","labels":["PROPERTY"],"properties":{"name":"name","uri":"schema-65"}}},
 {"type":"relationship","id":"75","label":"HAS_PROPERTY","properties":{"index":5},"start":{"id":"69","labels":["CLASS"],"properties":{"code":"sl","name":"Site Link","strict":false,"uri":"schema-63"}},"end":{"id":"73","labels":["PROPERTY"],"properties":{"name":"rating","uri":"schema-68"}}},
 {"type":"relationship","id":"76","label":"HAS_PROPERTY","properties":{"index":6},"start":{"id":"69","labels":["CLASS"],"properties":{"code":"sl","name":"Site Link","strict":false,"uri":"schema-63"}},"end":{"id":"74","labels":["PROPERTY"],"properties":{"name":"read","uri":"schema-69"}}},
 {"type":"relationship","id":"86","label":"HAS_PROPERTY","properties":{"index":3},"start":{"id":"34","labels":["CLASS"],"properties":{"code":"i","name":"Images","strict":false,"uri":"schema-77"}},"end":{"id":"130","labels":["PROPERTY"],"properties":{"name":"height","uri":"schema-129"}}},
 {"type":"relationship","id":"24","label":"HAS_PROPERTY","properties":{"index":1},"start":{"id":"82","labels":["CLASS"],"properties":{"code":"d","name":"Document","strict":false,"uri":"schema-80"}},"end":{"id":"83","labels":["PROPERTY"],"properties":{"name":"caption","uri":"schema-81"}}},
 {"type":"relationship","id":"89","label":"INSTANCE_OF","start":{"id":"69","labels":["CLASS"],"properties":{"code":"sl","name":"Site Link","strict":false,"uri":"schema-63"}},"end":{"id":"25","labels":["CLASS"],"properties":{"name":"Content Item","strict":false,"uri":"schema-15","no_datanodes":true}}},
 {"type":"relationship","id":"28","label":"INSTANCE_OF","start":{"id":"82","labels":["CLASS"],"properties":{"code":"d","name":"Document","strict":false,"uri":"schema-80"}},"end":{"id":"66","labels":["CLASS"],"properties":{"name":"Media","strict":false,"uri":"schema-60","no_datanodes":true}}},
 {"type":"relationship","id":"93","label":"HAS_PROPERTY","properties":{"index":2},"start":{"id":"132","labels":["CLASS"],"properties":{"name":"Plugin","strict":false,"uri":"schema-130"}},"end":{"id":"134","labels":["PROPERTY"],"properties":{"name":"location","uri":"schema-132"}}},
 {"type":"relationship","id":"31","label":"HAS_PROPERTY","properties":{"index":1},"start":{"id":"33","labels":["CLASS"],"properties":{"code":"n","name":"Notes","strict":false,"uri":"schema-23"}},"end":{"id":"84","labels":["PROPERTY"],"properties":{"name":"title","uri":"schema-82"}}},
 {"type":"relationship","id":"95","label":"HAS_PROPERTY","properties":{"index":1},"start":{"id":"132","labels":["CLASS"],"properties":{"name":"Plugin","strict":false,"uri":"schema-130"}},"end":{"id":"133","labels":["PROPERTY"],"properties":{"name":"code","uri":"schema-131"}}},
 {"type":"relationship","id":"96","label":"HAS_PLUGIN","start":{"id":"25","labels":["CLASS"],"properties":{"name":"Content Item","strict":false,"uri":"schema-15","no_datanodes":true}},"end":{"id":"132","labels":["CLASS"],"properties":{"name":"Plugin","strict":false,"uri":"schema-130"}}},
 {"type":"relationship","id":"98","label":"HAS_PROPERTY","properties":{"index":3},"start":{"id":"132","labels":["CLASS"],"properties":{"name":"Plugin","strict":false,"uri":"schema-130"}},"end":{"id":"131","labels":["PROPERTY"],"properties":{"name":"description","uri":"schema-133"}}},
 {"type":"relationship","id":"99","label":"INSTANCE_OF","start":{"id":"26","labels":["CLASS"],"properties":{"code":"cat","name":"Categories","strict":false,"uri":"schema-16"}},"end":{"id":"77","labels":["CLASS"],"properties":{"name":"Collections","strict":false,"uri":"schema-72","no_datanodes":true}}},
 {"type":"relationship","id":"101","label":"HAS_PROPERTY","properties":{"index":3},"start":{"id":"69","labels":["CLASS"],"properties":{"code":"sl","name":"Site Link","strict":false,"uri":"schema-63"}},"end":{"id":"71","labels":["PROPERTY"],"properties":{"name":"date","uri":"schema-66"}}},
 {"type":"relationship","id":"102","label":"has_index","start":{"id":"25","labels":["CLASS"],"properties":{"name":"Content Item","strict":false,"uri":"schema-15","no_datanodes":true}},"end":{"id":"113","labels":["CLASS"],"properties":{"name":"Indexer","strict":false,"uri":"schema-111"}}},
 {"type":"relationship","id":"103","label":"HAS_PROPERTY","properties":{"index":1},"start":{"id":"114","labels":["CLASS"],"properties":{"name":"Word","strict":false,"uri":"schema-112"}},"end":{"id":"115","labels":["PROPERTY"],"properties":{"name":"name","uri":"schema-113"}}},
 {"type":"relationship","id":"104","label":"occurs","start":{"id":"114","labels":["CLASS"],"properties":{"name":"Word","strict":false,"uri":"schema-112"}},"end":{"id":"113","labels":["CLASS"],"properties":{"name":"Indexer","strict":false,"uri":"schema-111"}}},
 {"type":"relationship","id":"42","label":"INSTANCE_OF","start":{"id":"32","labels":["CLASS"],"properties":{"code":"r","name":"Records","strict":false,"uri":"schema-22","no_datanodes":true}},"end":{"id":"25","labels":["CLASS"],"properties":{"name":"Content Item","strict":false,"uri":"schema-15","no_datanodes":true}}},
 {"type":"relationship","id":"107","label":"INSTANCE_OF","start":{"id":"33","labels":["CLASS"],"properties":{"code":"n","name":"Notes","strict":false,"uri":"schema-23"}},"end":{"id":"66","labels":["CLASS"],"properties":{"name":"Media","strict":false,"uri":"schema-60","no_datanodes":true}}},
 {"type":"relationship","id":"108","label":"HAS_PROPERTY","properties":{"index":1},"start":{"id":"37","labels":["CLASS"],"properties":{"code":"h","name":"Headers","strict":false,"uri":"schema-31"}},"end":{"id":"38","labels":["PROPERTY"],"properties":{"name":"text","uri":"schema-32"}}},
 {"type":"relationship","id":"109","label":"INSTANCE_OF","start":{"id":"37","labels":["CLASS"],"properties":{"code":"h","name":"Headers","strict":false,"uri":"schema-31"}},"end":{"id":"25","labels":["CLASS"],"properties":{"name":"Content Item","strict":false,"uri":"schema-15","no_datanodes":true}}},
 {"type":"relationship","id":"46","label":"HAS_PROPERTY","properties":{"index":4},"start":{"id":"69","labels":["CLASS"],"properties":{"code":"sl","name":"Site Link","strict":false,"uri":"schema-63"}},"end":{"id":"72","labels":["PROPERTY"],"properties":{"name":"comments","uri":"schema-67"}}},
 {"type":"relationship","id":"47","label":"HAS_PROPERTY","properties":{"index":1},"start":{"id":"26","labels":["CLASS"],"properties":{"code":"cat","name":"Categories","strict":false,"uri":"schema-16"}},"end":{"id":"27","labels":["PROPERTY"],"properties":{"name":"name","uri":"schema-17"}}},
 {"type":"relationship","id":"48","label":"HAS_PROPERTY","properties":{"index":2},"start":{"id":"26","labels":["CLASS"],"properties":{"code":"cat","name":"Categories","strict":false,"uri":"schema-16"}},"end":{"id":"28","labels":["PROPERTY"],"properties":{"name":"remarks","uri":"schema-18"}}},
 {"type":"relationship","id":"49","label":"BA_in_category","start":{"id":"25","labels":["CLASS"],"properties":{"name":"Content Item","strict":false,"uri":"schema-15","no_datanodes":true}},"end":{"id":"26","labels":["CLASS"],"properties":{"code":"cat","name":"Categories","strict":false,"uri":"schema-16"}}},
 {"type":"relationship","id":"115","label":"BA_subcategory_of","start":{"id":"26","labels":["CLASS"],"properties":{"code":"cat","name":"Categories","strict":false,"uri":"schema-16"}},"end":{"id":"26","labels":["CLASS"],"properties":{"code":"cat","name":"Categories","strict":false,"uri":"schema-16"}}},
 {"type":"relationship","id":"117","label":"BA_see_also","start":{"id":"26","labels":["CLASS"],"properties":{"code":"cat","name":"Categories","strict":false,"uri":"schema-16"}},"end":{"id":"26","labels":["CLASS"],"properties":{"code":"cat","name":"Categories","strict":false,"uri":"schema-16"}}},
 {"type":"relationship","id":"59","label":"HAS_PROPERTY","properties":{"index":1},"start":{"id":"66","labels":["CLASS"],"properties":{"name":"Media","strict":false,"uri":"schema-60","no_datanodes":true}},"end":{"id":"67","labels":["PROPERTY"],"properties":{"name":"basename","uri":"schema-61"}}},
 {"type":"relationship","id":"60","label":"HAS_PROPERTY","properties":{"index":2},"start":{"id":"66","labels":["CLASS"],"properties":{"name":"Media","strict":false,"uri":"schema-60","no_datanodes":true}},"end":{"id":"68","labels":["PROPERTY"],"properties":{"name":"suffix","uri":"schema-62"}}},
 {"type":"relationship","id":"61","label":"INSTANCE_OF","start":{"id":"66","labels":["CLASS"],"properties":{"name":"Media","strict":false,"uri":"schema-60","no_datanodes":true}},"end":{"id":"25","labels":["CLASS"],"properties":{"name":"Content Item","strict":false,"uri":"schema-15","no_datanodes":true}}}
]